examples/australian_federal_hansard/cluster_timing_test.py
examples/australian_federal_hansard/cluster_timing_test_new.py
examples/australian_federal_hansard/hansard_corpus.py
examples/australian_federal_hansard/prepare_education_crisis_data_for_annotation.py
examples/stackoverflow/visuals.py
examples/stackoverflow/data/cluster_timing_test.py
examples/stackoverflow/data/cluster_timing_test_new.py
examples/twitter/ingest_tweets.py
hyperreal/__init__.py
hyperreal/_index_schema.py
hyperreal/cli.py
hyperreal/corpus.py
hyperreal/db_utilities.py
hyperreal/index.py
hyperreal/server.py
hyperreal/utilities.py
hyperreal/value_handlers.py
hyperreal/templates/__init__.py
hyperreal/templates/base.html
hyperreal/templates/cluster.html
hyperreal/templates/details.html
hyperreal/templates/index.html
hyperreal/templates/index_listing.html
hyperreal/templates/macros.html
hyperreal-0.6.1.dist-info/LICENSE.txt
hyperreal-0.6.1.dist-info/METADATA
hyperreal-0.6.1.dist-info/WHEEL
hyperreal-0.6.1.dist-info/entry_points.txt
hyperreal-0.6.1.dist-info/top_level.txt
hyperreal-0.6.1.dist-info/RECORD
