Metadata-Version: 2.1
Name: hyperreal
Version: 0.6.1
Summary: Hyperreal is a library and tool for intepretive topic modelling.
Author: Sam Hames, Kateryna Kasianenko
License: 
Project-URL: Repository, https://hyperreal.app
Project-URL: Homepage, https://hyperreal.app
Classifier: Development Status :: 3 - Alpha
Classifier: Intended Audience :: Science/Research
Classifier: License :: OSI Approved :: Apache Software License
Requires-Python: >=3.9.0
License-File: LICENSE.txt
Requires-Dist: click >=8.1.0
Requires-Dist: jinja2 >=3.1.0
Requires-Dist: pyroaring >=0.3.4
Requires-Dist: regex >=2022.4.24
Requires-Dist: cherrypy >=18.6.0
Requires-Dist: python-dateutil >=2.8.0
Requires-Dist: lxml
Provides-Extra: dev
Requires-Dist: pytest ; extra == 'dev'
Requires-Dist: black ; extra == 'dev'
Requires-Dist: tox ; extra == 'dev'
Requires-Dist: requests ; extra == 'dev'
Requires-Dist: pylint ; extra == 'dev'
Requires-Dist: isort ; extra == 'dev'
Provides-Extra: stackexchange
Requires-Dist: py7zr >=0.21.0 ; extra == 'stackexchange'
